streamdeck_sdk/__init__.py
streamdeck_sdk/event_routings.py
streamdeck_sdk/logger.py
streamdeck_sdk/sdk.py
streamdeck_sdk/mixins/__init__.py
streamdeck_sdk/mixins/debug_server_mixin.py
streamdeck_sdk/mixins/event_routing_mixin.py
streamdeck_sdk/mixins/handle_event_mixins.py
streamdeck_sdk/mixins/send_event_mixins.py
streamdeck_sdk/sd_objs/__init__.py
streamdeck_sdk/sd_objs/registration_objs.py
streamdeck_sdk/sd_objs/events_received_objs/__init__.py
streamdeck_sdk/sd_objs/events_received_objs/application_did_launch.py
streamdeck_sdk/sd_objs/events_received_objs/application_did_terminate.py
streamdeck_sdk/sd_objs/events_received_objs/device_did_connect.py
streamdeck_sdk/sd_objs/events_received_objs/device_did_disconnect.py
streamdeck_sdk/sd_objs/events_received_objs/dial_down.py
streamdeck_sdk/sd_objs/events_received_objs/dial_rotate.py
streamdeck_sdk/sd_objs/events_received_objs/dial_up.py
streamdeck_sdk/sd_objs/events_received_objs/did_receive_deep_link.py
streamdeck_sdk/sd_objs/events_received_objs/did_receive_global_settings.py
streamdeck_sdk/sd_objs/events_received_objs/did_receive_settings.py
streamdeck_sdk/sd_objs/events_received_objs/key_down.py
streamdeck_sdk/sd_objs/events_received_objs/key_up.py
streamdeck_sdk/sd_objs/events_received_objs/property_inspector_did_appear.py
streamdeck_sdk/sd_objs/events_received_objs/property_inspector_did_disappear.py
streamdeck_sdk/sd_objs/events_received_objs/send_to_plugin.py
streamdeck_sdk/sd_objs/events_received_objs/send_to_property_inspector.py
streamdeck_sdk/sd_objs/events_received_objs/system_did_wake_up.py
streamdeck_sdk/sd_objs/events_received_objs/title_parameters_did_change.py
streamdeck_sdk/sd_objs/events_received_objs/touch_tap.py
streamdeck_sdk/sd_objs/events_received_objs/will_appear.py
streamdeck_sdk/sd_objs/events_received_objs/will_disappear.py
streamdeck_sdk/sd_objs/events_received_objs/assets/__init__.py
streamdeck_sdk/sd_objs/events_received_objs/assets/controller_enum.py
streamdeck_sdk-1.2.1.dist-info/LICENSE
streamdeck_sdk-1.2.1.dist-info/METADATA
streamdeck_sdk-1.2.1.dist-info/WHEEL
streamdeck_sdk-1.2.1.dist-info/top_level.txt
streamdeck_sdk-1.2.1.dist-info/RECORD
